githubhelp/__init__.py
githubhelp/gh.py
github_help_wanted-1.1.dist-info/LICENSE.md
github_help_wanted-1.1.dist-info/METADATA
github_help_wanted-1.1.dist-info/WHEEL
github_help_wanted-1.1.dist-info/entry_points.txt
github_help_wanted-1.1.dist-info/top_level.txt
github_help_wanted-1.1.dist-info/RECORD
